barbara3.py
barbara_updater-4.3.15.dist-info/METADATA
barbara_updater-4.3.15.dist-info/WHEEL
barbara_updater-4.3.15.dist-info/top_level.txt
barbara_updater-4.3.15.dist-info/RECORD
