Metadata-Version: 2.4
Name: barbara_updater
Version: 4.3.15
Summary: weather observer
Author: santod
Dynamic: author
Dynamic: summary
